constants.py
tracker/__init__.py
tracker/__main__.py
tracker/phone_tracker.py
phone_locator-0.1.1.dist-info/METADATA
phone_locator-0.1.1.dist-info/WHEEL
phone_locator-0.1.1.dist-info/entry_points.txt
phone_locator-0.1.1.dist-info/licenses/LICENSE
phone_locator-0.1.1.dist-info/RECORD
