Metadata-Version: 2.4
Name: phone-locator
Version: 0.1.1
Summary: Phone number geolocation and carrier information tool
Project-URL: Homepage, https://github.com/jmeiracorbal/phone-locator
Project-URL: Repository, https://github.com/jmeiracorbal/phone-locator
Project-URL: Issues, https://github.com/jmeiracorbal/phone-locator/issues
Author: jmeiracorbal
License: MIT License
License-File: LICENSE
Keywords: carrier,geolocation,lookup,osint,phone,phonenumbers
Classifier: Development Status :: 4 - Beta
Classifier: Intended Audience :: Developers
Classifier: License :: OSI Approved :: MIT License
Classifier: Programming Language :: Python :: 3
Classifier: Programming Language :: Python :: 3.8
Classifier: Programming Language :: Python :: 3.9
Classifier: Programming Language :: Python :: 3.10
Classifier: Programming Language :: Python :: 3.11
Classifier: Programming Language :: Python :: 3.12
Classifier: Programming Language :: Python :: 3.13
Classifier: Topic :: Software Development :: Libraries :: Python Modules
Classifier: Topic :: Utilities
Requires-Python: <3.14,>=3.8
Requires-Dist: phonenumbers>=8.13.0
Provides-Extra: dev
Requires-Dist: auto-py-to-exe>=2.36.0; extra == 'dev'
Requires-Dist: pyinstaller>=6.15.0; extra == 'dev'
